pgpow/__init__.py
pgpow/__main__.py
pgpow/cli.py
pgpow-0.1.dist-info/WHEEL
pgpow-0.1.dist-info/entry_points.txt
pgpow-0.1.dist-info/METADATA
pgpow-0.1.dist-info/RECORD
