Metadata-Version: 2.3
Name: pgpow
Version: 0.1
Summary: A command line toolkit for working with PostgreSQL.
Author: Rob Young
License: Apache-2.0
Classifier: License :: OSI Approved :: Apache Software License
Classifier: Development Status :: 3 - Alpha
Classifier: Environment :: Console
Classifier: Intended Audience :: Developers
Classifier: Intended Audience :: System Administrators
Classifier: Operating System :: OS Independent
Classifier: Programming Language :: Python :: 3 :: Only
Classifier: Programming Language :: SQL
Classifier: Topic :: Database
Requires-Dist: click
Requires-Dist: pytest ; extra == 'test'
Requires-Python: >=3.10
Project-URL: CI, https://github.com/robyoung/pgpow/actions
Project-URL: Changelog, https://github.com/robyoung/pgpow/releases
Project-URL: Homepage, https://github.com/robyoung/pgpow
Project-URL: Issues, https://github.com/robyoung/pgpow/issues
Provides-Extra: test
